quantifiles/__init__.py
quantifiles/data.py
quantifiles/main.py
quantifiles/path.py
quantifiles/units.py
quantifiles/watcher.py
quantifiles/plot/__init__.py
quantifiles/plot/autoplot.py
quantifiles/plot/baseplot.py
quantifiles/plot/colorplot.py
quantifiles/plot/header.py
quantifiles/plot/lineplot.py
quantifiles/plot/snapshot.py
quantifiles/plot/utils.py
quantifiles/plot/window.py
tests/__init__.py
tests/test_data.py
tests/test_units.py
quantifiles-0.2.1.dist-info/LICENSE
quantifiles-0.2.1.dist-info/METADATA
quantifiles-0.2.1.dist-info/WHEEL
quantifiles-0.2.1.dist-info/entry_points.txt
quantifiles-0.2.1.dist-info/top_level.txt
quantifiles-0.2.1.dist-info/RECORD
