Metadata-Version: 2.1
Name: quantifiles
Version: 0.2.1
Summary: Simple databrowser for quantify datasets.
Home-page: https://gitlab.com/dcrielaard/quantifiles
Author: Damien Crielaard
Author-email: damiencrielaard@gmail.com
License: BSD 2-Clause License        
Platform: UNKNOWN
Requires-Python: >=3.7
License-File: LICENSE
Requires-Dist: numpy
Requires-Dist: matplotlib
Requires-Dist: scipy
Requires-Dist: pandas
Requires-Dist: xarray
Requires-Dist: filelock
Requires-Dist: qcodes
Requires-Dist: pyqtgraph
Requires-Dist: pyqt5
Requires-Dist: quantify-core
Provides-Extra: test
Requires-Dist: black ; extra == 'test'
Requires-Dist: pytest ; extra == 'test'
